d2dcn/__init__.py
d2dcn/d2dcn.py
d2dcn-0.5.5.dist-info/LICENSE
d2dcn-0.5.5.dist-info/METADATA
d2dcn-0.5.5.dist-info/WHEEL
d2dcn-0.5.5.dist-info/top_level.txt
d2dcn-0.5.5.dist-info/RECORD
