Metadata-Version: 2.1
Name: d2dcn
Version: 0.5.5
Summary: UNKNOWN
Home-page: https://github.com/qeyup/d2dcn-python
Author: Javier Moreno Garcia
Author-email: jgmore@gmail.com
License: UNKNOWN
Platform: UNKNOWN
Requires-Dist: SharedTableBroker (>=0.1.3)
Requires-Dist: psutil
Requires-Dist: pyroute2
